kaggle_dataset_creator/__init__.py
kaggle_dataset_creator/exceptions.py
kaggle_dataset_creator/kaggle_dataset_creator.py
kaggle_dataset_creator/message.py
kaggle_dataset_creator/random_string.py
kaggle_dataset_creator-0.0.1.dist-info/LICENSE
kaggle_dataset_creator-0.0.1.dist-info/METADATA
kaggle_dataset_creator-0.0.1.dist-info/WHEEL
kaggle_dataset_creator-0.0.1.dist-info/top_level.txt
kaggle_dataset_creator-0.0.1.dist-info/RECORD
