Metadata-Version: 2.1
Name: kaggle-dataset-creator
Version: 0.0.1
Summary: A Python package to generate csv/json from command line. It allows you to create CSV/JSON files by asking you to manually enter data for each cells row by row in Terminal (Windows CMD / Bash).
Home-page: https://github.com/hygull/kaggle_dataset_creator.git
Author: Rishikesh Agrawani
Author-email: rishikesh0014051992@gmail.com
License: UNKNOWN
Keywords: CSV,JSON,kaggle,dataset,Python 3,Windows,Linux,MAC,Command line
Platform: UNKNOWN
Classifier: Programming Language :: Python :: 3
Classifier: License :: OSI Approved :: MIT License
Classifier: Operating System :: OS Independent
Requires-Python: >=3
Requires-Dist: pandas (>=0.23.4)
Requires-Dist: colorama (>=0.4.1)
Requires-Dist: numpy (>=1.15.4)
